graphene_veneer/__init__.py
graphene_veneer/__main__.py
graphene_veneer-0.0.1.dev1.dist-info/LICENSE
graphene_veneer-0.0.1.dev1.dist-info/METADATA
graphene_veneer-0.0.1.dev1.dist-info/WHEEL
graphene_veneer-0.0.1.dev1.dist-info/top_level.txt
graphene_veneer-0.0.1.dev1.dist-info/RECORD
