Metadata-Version: 2.1
Name: graphene-veneer
Version: 0.0.1.dev1
Summary: Model-agnostic code generator for Graphene. Define a data mapper between your model and graphql. Let Graphene Veneer take care of the rest.
Home-page: UNKNOWN
Author: Kuni Natsuki
Author-email: kuni.natsuki@gmail.com
License: UNKNOWN
Platform: UNKNOWN
Requires-Python: >=3.8
License-File: LICENSE
